{
  "editor:toggle-code": [
    {
      "modifiers": [
        "Shift"
      ],
      "key": "`"
    }
  ],
  "workspace:split-horizontal": [
    {
      "modifiers": [
        "Mod",
        "Meta"
      ],
      "key": "ArrowDown"
    }
  ],
  "obsidian-minimal-settings:toggle-minimal-focus-mode": [
    {
      "modifiers": [
        "Alt",
        "Mod"
      ],
      "key": "F"
    }
  ],
  "templater-obsidian:Templates/Notes.md": [
    {
      "modifiers": [
        "Alt",
        "Mod"
      ],
      "key": "I"
    }
  ],
  "url-into-selection:paste-url-into-selection": [
    {
      "modifiers": [
        "Mod",
        "Shift"
      ],
      "key": "V"
    }
  ],
  "theme:use-light": [],
  "theme:use-dark": [],
  "workspace:next-tab": [
    {
      "modifiers": [
        "Alt",
        "Mod"
      ],
      "key": "ArrowRight"
    }
  ],
  "workspace:previous-tab": [
    {
      "modifiers": [
        "Alt",
        "Mod"
      ],
      "key": "ArrowLeft"
    }
  ],
  "obsidian-hider:toggle-tab-containers": [
    {
      "modifiers": [
        "Alt",
        "Shift"
      ],
      "key": "T"
    }
  ],
  "obsidian-hider:toggle-hider-status": [],
  "obsidian-hider:toggle-app-ribbon": [
    {
      "modifiers": [
        "Alt",
        "Shift"
      ],
      "key": "H"
    }
  ],
  "app:go-forward": [
    {
      "modifiers": [
        "Ctrl",
        "Mod"
      ],
      "key": "ArrowRight"
    }
  ],
  "workspace:undo-close-pane": [],
  "app:toggle-left-sidebar": [
    {
      "modifiers": [
        "Mod",
        "Shift"
      ],
      "key": "E"
    }
  ],
  "editor:set-heading-4": [
    {
      "modifiers": [
        "Mod",
        "Shift"
      ],
      "key": "J"
    }
  ],
  "editor:set-heading-2": [
    {
      "modifiers": [
        "Mod",
        "Shift"
      ],
      "key": "T"
    }
  ],
  "editor:set-heading-3": [
    {
      "modifiers": [
        "Mod",
        "Shift"
      ],
      "key": "H"
    }
  ],
  "editor:insert-wikilink": [
    {
      "modifiers": [
        "Mod",
        "Shift"
      ],
      "key": "L"
    }
  ],
  "editor:delete-paragraph": [],
  "workspace:goto-last-tab": [],
  "app:toggle-right-sidebar": [
    {
      "modifiers": [
        "Mod",
        "Shift"
      ],
      "key": "R"
    }
  ],
  "file-explorer:new-file": [],
  "app:go-back": [
    {
      "modifiers": [
        "Ctrl",
        "Mod"
      ],
      "key": "ArrowLeft"
    }
  ],
  "editor:set-heading-5": [
    {
      "modifiers": [
        "Mod",
        "Shift"
      ],
      "key": "K"
    }
  ],
  "templater-obsidian:insert-templater": [
    {
      "modifiers": [
        "Mod",
        "Shift"
      ],
      "key": "I"
    }
  ],
  "quick-latex:addInlineMath": [
    {
      "modifiers": [
        "Mod"
      ],
      "key": "M"
    }
  ]
}